bough/__init__.py
bough/analyzer.py
bough/cli.py
bough/config.py
bough/formatters.py
bough/git.py
bough-0.3.1.dist-info/METADATA
bough-0.3.1.dist-info/WHEEL
bough-0.3.1.dist-info/entry_points.txt
bough-0.3.1.dist-info/licenses/LICENSE
bough-0.3.1.dist-info/RECORD
