Metadata-Version: 2.4
Name: bough
Version: 0.3.1
Summary: bough is a tool to determine which uv workspace packages need rebuilding based on git changes
Project-URL: Repository, https://github.com/20treeAI/bough.git
Author-email: Andrew Nichols <andrew.nichols@overstory.com>
License-Expression: MIT
License-File: LICENSE
Requires-Python: >=3.12
Requires-Dist: gitpython>=3.1.0
Requires-Dist: packaging>=21.0
Requires-Dist: pyyaml>=6.0
